versionator/__init__.py
versionator/__main__.py
versionator-0.0.5.dist-info/LICENSE
versionator-0.0.5.dist-info/METADATA
versionator-0.0.5.dist-info/WHEEL
versionator-0.0.5.dist-info/entry_points.txt
versionator-0.0.5.dist-info/top_level.txt
versionator-0.0.5.dist-info/RECORD
