Metadata-Version: 2.1
Name: versionator
Version: 0.0.5
Summary: A tool for managing Python packages
Home-page: https://ktpanda.org/software/versionator
Author: Katie Rust
Author-email: katie@ktpanda.org
License: MIT License
Classifier: Programming Language :: Python :: 3
Classifier: License :: OSI Approved :: MIT License
Classifier: Operating System :: OS Independent
Requires-Python: >=3.6
License-File: LICENSE
Requires-Dist: argcomplete (>=2.0.0)
